{
  "account": {
    "arrayChildren": ["accountJournal", "accountStatement"]
  },
  "accountTransaction": {
    "arrayChildren": ["accountJournal"]
  },
  "insuranceProvider": {},
  "loanNumberIdsCache": {
    "singleChildren": ["memberLoan"]
  },
  "member": {
    "arrayChildren": [
      "dividends",
      "memberDependant",
      "memberLoan",
      "memberSaving",
      "memberShares",
      "notification"
    ],
    "singleChildren": ["memberContact", "memberLoanSettlement"]
  },
  "memberBusiness": {
    "singleChildren": [
      "memberBusinessVerification",
      "memberLastYearBusinessHistory",
      "memberNextYearBusinessProjection"
    ]
  },
  "memberIdsCache": {
    "singleChildren": ["member"]
  },
  "memberLoan": {
    "arrayChildren": [
      "memberLoanLiability",
      "memberLoanPaymentSchedule",
      "memberLoanSecurity",
      "memberLoanWitness"
    ],
    "singleChildren": [
      "memberBusiness",
      "memberLoanApproval",
      "memberLoanDisbursement",
      "memberOccupation"
    ]
  },
  "memberLoanApproval": {
    "singleChildren": ["memberLoanVerification"]
  },
  "memberLoanPayment": {
    "arrayChildren": ["memberLoanPaymentDetail", "memberLoanTax"]
  },
  "memberLoanPaymentSchedule": {
    "singleChildren": ["memberLoanPayment"]
  },
  "memberLoanType": {},
  "memberOccupation": {
    "singleChildren": ["memberOccupationVerification"]
  },
  "memberSaving": {
    "arrayChildren": [
      "memberSavingDeposit",
      "memberSavingInterest",
      "memberSavingWithdrawal",
      "sharesDepositReceipt",
      "sharesDepositWithdraw"
    ]
  },
  "memberSavingsIdsCache": {
    "singleChildren": ["memberSaving"]
  },
  "memberSharesIdsCache": {
    "singleChildren": ["memberShares"]
  },
  "savingsType": {
    "arrayChildren": ["memberSaving", "savingsRate"]
  },
  "taxRate": {},
  "user": {},
  "userRole": {}
}
